{"nodes": [{"id": "volumes_code_personal_teman_lari_app_enums_badge_php", "label": "Badge.php", "file_type": "code", "source_file": "app/Enums/Badge.php", "source_location": "L1"}, {"id": "enums_badge_label", "label": "label()", "file_type": "code", "source_file": "app/Enums/Badge.php", "source_location": "L33"}, {"id": "enums_badge_tracked", "label": "tracked()", "file_type": "code", "source_file": "app/Enums/Badge.php", "source_location": "L62"}, {"id": "enums_badge_labels", "label": "labels()", "file_type": "code", "source_file": "app/Enums/Badge.php", "source_location": "L75"}], "edges": [{"source": "volumes_code_personal_teman_lari_app_enums_badge_php", "target": "enums_badge_label", "relation": "contains", "confidence": "EXTRACTED", "source_file": "app/Enums/Badge.php", "source_location": "L33", "weight": 1.0}, {"source": "volumes_code_personal_teman_lari_app_enums_badge_php", "target": "enums_badge_tracked", "relation": "contains", "confidence": "EXTRACTED", "source_file": "app/Enums/Badge.php", "source_location": "L62", "weight": 1.0}, {"source": "volumes_code_personal_teman_lari_app_enums_badge_php", "target": "enums_badge_labels", "relation": "contains", "confidence": "EXTRACTED", "source_file": "app/Enums/Badge.php", "source_location": "L75", "weight": 1.0}, {"source": "enums_badge_labels", "target": "enums_badge_label", "relation": "calls", "context": "call", "confidence": "EXTRACTED", "source_file": "app/Enums/Badge.php", "source_location": "L79", "weight": 1.0}], "raw_calls": [{"caller_nid": "enums_badge_labels", "callee": "array_combine", "is_member_call": false, "source_file": "/Volumes/Code/personal/teman-lari/app/Enums/Badge.php", "source_location": "L77"}, {"caller_nid": "enums_badge_labels", "callee": "array_map", "is_member_call": false, "source_file": "/Volumes/Code/personal/teman-lari/app/Enums/Badge.php", "source_location": "L78"}, {"caller_nid": "enums_badge_labels", "callee": "self", "is_member_call": false, "source_file": "/Volumes/Code/personal/teman-lari/app/Enums/Badge.php", "source_location": "L78"}, {"caller_nid": "enums_badge_labels", "callee": "array_map", "is_member_call": false, "source_file": "/Volumes/Code/personal/teman-lari/app/Enums/Badge.php", "source_location": "L79"}, {"caller_nid": "enums_badge_labels", "callee": "self", "is_member_call": false, "source_file": "/Volumes/Code/personal/teman-lari/app/Enums/Badge.php", "source_location": "L79"}]}